{
  "id": "d7703c87-bab5-4a29-b272-d0e8076bdcaf",
  "prevId": "946896b6-67f6-47f0-87b9-1376597d0100",
  "version": "7",
  "dialect": "postgresql",
  "tables": {
    "public.death_events": {
      "name": "death_events",
      "schema": "",
      "columns": {
        "id": {
          "name": "id",
          "type": "uuid",
          "primaryKey": true,
          "notNull": true,
          "default": "gen_random_uuid()"
        },
        "game_id": {
          "name": "game_id",
          "type": "uuid",
          "primaryKey": false,
          "notNull": true
        },
        "player_id": {
          "name": "player_id",
          "type": "uuid",
          "primaryKey": false,
          "notNull": true
        },
        "marked_by": {
          "name": "marked_by",
          "type": "uuid",
          "primaryKey": false,
          "notNull": false
        },
        "created_at": {
          "name": "created_at",
          "type": "timestamp",
          "primaryKey": false,
          "notNull": true,
          "default": "now()"
        }
      },
      "indexes": {},
      "foreignKeys": {
        "death_events_game_id_game_instances_id_fk": {
          "name": "death_events_game_id_game_instances_id_fk",
          "tableFrom": "death_events",
          "tableTo": "game_instances",
          "columnsFrom": [
            "game_id"
          ],
          "columnsTo": [
            "id"
          ],
          "onDelete": "no action",
          "onUpdate": "no action"
        },
        "death_events_player_id_players_in_game_id_fk": {
          "name": "death_events_player_id_players_in_game_id_fk",
          "tableFrom": "death_events",
          "tableTo": "players_in_game",
          "columnsFrom": [
            "player_id"
          ],
          "columnsTo": [
            "id"
          ],
          "onDelete": "no action",
          "onUpdate": "no action"
        },
        "death_events_marked_by_user_accounts_id_fk": {
          "name": "death_events_marked_by_user_accounts_id_fk",
          "tableFrom": "death_events",
          "tableTo": "user_accounts",
          "columnsFrom": [
            "marked_by"
          ],
          "columnsTo": [
            "id"
          ],
          "onDelete": "no action",
          "onUpdate": "no action"
        }
      },
      "compositePrimaryKeys": {},
      "uniqueConstraints": {},
      "policies": {},
      "checkConstraints": {},
      "isRLSEnabled": false
    },
    "public.game_configs": {
      "name": "game_configs",
      "schema": "",
      "columns": {
        "id": {
          "name": "id",
          "type": "uuid",
          "primaryKey": true,
          "notNull": true,
          "default": "gen_random_uuid()"
        },
        "game_id": {
          "name": "game_id",
          "type": "uuid",
          "primaryKey": false,
          "notNull": true
        },
        "min_players": {
          "name": "min_players",
          "type": "integer",
          "primaryKey": false,
          "notNull": true,
          "default": 4
        },
        "max_players": {
          "name": "max_players",
          "type": "integer",
          "primaryKey": false,
          "notNull": true,
          "default": 15
        },
        "impostor_count": {
          "name": "impostor_count",
          "type": "integer",
          "primaryKey": false,
          "notNull": true,
          "default": 1
        },
        "game_duration_seconds": {
          "name": "game_duration_seconds",
          "type": "integer",
          "primaryKey": false,
          "notNull": true,
          "default": 1800
        },
        "meeting_duration_seconds": {
          "name": "meeting_duration_seconds",
          "type": "integer",
          "primaryKey": false,
          "notNull": true,
          "default": 120
        },
        "sabotage_duration_seconds": {
          "name": "sabotage_duration_seconds",
          "type": "integer",
          "primaryKey": false,
          "notNull": true,
          "default": 60
        },
        "sabotage_cooldown_seconds": {
          "name": "sabotage_cooldown_seconds",
          "type": "integer",
          "primaryKey": false,
          "notNull": true,
          "default": 30
        },
        "task_validation_mode": {
          "name": "task_validation_mode",
          "type": "task_validation_mode",
          "typeSchema": "public",
          "primaryKey": false,
          "notNull": true,
          "default": "'ANY_PLAYER'"
        },
        "oxygen_code": {
          "name": "oxygen_code",
          "type": "varchar(4)",
          "primaryKey": false,
          "notNull": true,
          "default": "'1234'"
        },
        "reveal_role_on_eject": {
          "name": "reveal_role_on_eject",
          "type": "boolean",
          "primaryKey": false,
          "notNull": true,
          "default": true
        },
        "single_use_sabotage": {
          "name": "single_use_sabotage",
          "type": "boolean",
          "primaryKey": false,
          "notNull": true,
          "default": true
        },
        "tasks_json": {
          "name": "tasks_json",
          "type": "jsonb",
          "primaryKey": false,
          "notNull": true,
          "default": "'[]'::jsonb"
        },
        "manual_roles": {
          "name": "manual_roles",
          "type": "jsonb",
          "primaryKey": false,
          "notNull": false
        }
      },
      "indexes": {},
      "foreignKeys": {
        "game_configs_game_id_game_instances_id_fk": {
          "name": "game_configs_game_id_game_instances_id_fk",
          "tableFrom": "game_configs",
          "tableTo": "game_instances",
          "columnsFrom": [
            "game_id"
          ],
          "columnsTo": [
            "id"
          ],
          "onDelete": "no action",
          "onUpdate": "no action"
        }
      },
      "compositePrimaryKeys": {},
      "uniqueConstraints": {
        "game_configs_game_id_unique": {
          "name": "game_configs_game_id_unique",
          "nullsNotDistinct": false,
          "columns": [
            "game_id"
          ]
        }
      },
      "policies": {},
      "checkConstraints": {},
      "isRLSEnabled": false
    },
    "public.game_events": {
      "name": "game_events",
      "schema": "",
      "columns": {
        "id": {
          "name": "id",
          "type": "uuid",
          "primaryKey": true,
          "notNull": true,
          "default": "gen_random_uuid()"
        },
        "game_id": {
          "name": "game_id",
          "type": "uuid",
          "primaryKey": false,
          "notNull": true
        },
        "type": {
          "name": "type",
          "type": "varchar(50)",
          "primaryKey": false,
          "notNull": true
        },
        "payload": {
          "name": "payload",
          "type": "jsonb",
          "primaryKey": false,
          "notNull": true,
          "default": "'{}'::jsonb"
        },
        "created_at": {
          "name": "created_at",
          "type": "timestamp",
          "primaryKey": false,
          "notNull": true,
          "default": "now()"
        }
      },
      "indexes": {},
      "foreignKeys": {
        "game_events_game_id_game_instances_id_fk": {
          "name": "game_events_game_id_game_instances_id_fk",
          "tableFrom": "game_events",
          "tableTo": "game_instances",
          "columnsFrom": [
            "game_id"
          ],
          "columnsTo": [
            "id"
          ],
          "onDelete": "no action",
          "onUpdate": "no action"
        }
      },
      "compositePrimaryKeys": {},
      "uniqueConstraints": {},
      "policies": {},
      "checkConstraints": {},
      "isRLSEnabled": false
    },
    "public.game_instances": {
      "name": "game_instances",
      "schema": "",
      "columns": {
        "id": {
          "name": "id",
          "type": "uuid",
          "primaryKey": true,
          "notNull": true,
          "default": "gen_random_uuid()"
        },
        "code": {
          "name": "code",
          "type": "varchar(6)",
          "primaryKey": false,
          "notNull": true
        },
        "status": {
          "name": "status",
          "type": "game_status",
          "typeSchema": "public",
          "primaryKey": false,
          "notNull": true,
          "default": "'DRAFT'"
        },
        "phase": {
          "name": "phase",
          "type": "game_phase",
          "typeSchema": "public",
          "primaryKey": false,
          "notNull": false
        },
        "created_by": {
          "name": "created_by",
          "type": "uuid",
          "primaryKey": false,
          "notNull": true
        },
        "game_timer_ends_at": {
          "name": "game_timer_ends_at",
          "type": "timestamp",
          "primaryKey": false,
          "notNull": false
        },
        "created_at": {
          "name": "created_at",
          "type": "timestamp",
          "primaryKey": false,
          "notNull": true,
          "default": "now()"
        },
        "updated_at": {
          "name": "updated_at",
          "type": "timestamp",
          "primaryKey": false,
          "notNull": true,
          "default": "now()"
        }
      },
      "indexes": {},
      "foreignKeys": {
        "game_instances_created_by_user_accounts_id_fk": {
          "name": "game_instances_created_by_user_accounts_id_fk",
          "tableFrom": "game_instances",
          "tableTo": "user_accounts",
          "columnsFrom": [
            "created_by"
          ],
          "columnsTo": [
            "id"
          ],
          "onDelete": "no action",
          "onUpdate": "no action"
        }
      },
      "compositePrimaryKeys": {},
      "uniqueConstraints": {
        "game_instances_code_unique": {
          "name": "game_instances_code_unique",
          "nullsNotDistinct": false,
          "columns": [
            "code"
          ]
        }
      },
      "policies": {},
      "checkConstraints": {},
      "isRLSEnabled": false
    },
    "public.guest_sessions": {
      "name": "guest_sessions",
      "schema": "",
      "columns": {
        "id": {
          "name": "id",
          "type": "uuid",
          "primaryKey": true,
          "notNull": true,
          "default": "gen_random_uuid()"
        },
        "pseudo": {
          "name": "pseudo",
          "type": "varchar(30)",
          "primaryKey": false,
          "notNull": true
        },
        "session_token": {
          "name": "session_token",
          "type": "text",
          "primaryKey": false,
          "notNull": true
        },
        "reconnect_token": {
          "name": "reconnect_token",
          "type": "text",
          "primaryKey": false,
          "notNull": true
        },
        "game_id": {
          "name": "game_id",
          "type": "uuid",
          "primaryKey": false,
          "notNull": true
        },
        "created_at": {
          "name": "created_at",
          "type": "timestamp",
          "primaryKey": false,
          "notNull": true,
          "default": "now()"
        },
        "last_seen_at": {
          "name": "last_seen_at",
          "type": "timestamp",
          "primaryKey": false,
          "notNull": true,
          "default": "now()"
        }
      },
      "indexes": {},
      "foreignKeys": {
        "guest_sessions_game_id_game_instances_id_fk": {
          "name": "guest_sessions_game_id_game_instances_id_fk",
          "tableFrom": "guest_sessions",
          "tableTo": "game_instances",
          "columnsFrom": [
            "game_id"
          ],
          "columnsTo": [
            "id"
          ],
          "onDelete": "no action",
          "onUpdate": "no action"
        }
      },
      "compositePrimaryKeys": {},
      "uniqueConstraints": {
        "guest_sessions_session_token_unique": {
          "name": "guest_sessions_session_token_unique",
          "nullsNotDistinct": false,
          "columns": [
            "session_token"
          ]
        },
        "guest_sessions_reconnect_token_unique": {
          "name": "guest_sessions_reconnect_token_unique",
          "nullsNotDistinct": false,
          "columns": [
            "reconnect_token"
          ]
        }
      },
      "policies": {},
      "checkConstraints": {},
      "isRLSEnabled": false
    },
    "public.meeting_states": {
      "name": "meeting_states",
      "schema": "",
      "columns": {
        "id": {
          "name": "id",
          "type": "uuid",
          "primaryKey": true,
          "notNull": true,
          "default": "gen_random_uuid()"
        },
        "game_id": {
          "name": "game_id",
          "type": "uuid",
          "primaryKey": false,
          "notNull": true
        },
        "state": {
          "name": "state",
          "type": "meeting_state",
          "typeSchema": "public",
          "primaryKey": false,
          "notNull": true,
          "default": "'IDLE'"
        },
        "triggered_by": {
          "name": "triggered_by",
          "type": "uuid",
          "primaryKey": false,
          "notNull": false
        },
        "is_body_report": {
          "name": "is_body_report",
          "type": "boolean",
          "primaryKey": false,
          "notNull": true,
          "default": false
        },
        "timer_ends_at": {
          "name": "timer_ends_at",
          "type": "timestamp",
          "primaryKey": false,
          "notNull": false
        },
        "created_at": {
          "name": "created_at",
          "type": "timestamp",
          "primaryKey": false,
          "notNull": true,
          "default": "now()"
        }
      },
      "indexes": {},
      "foreignKeys": {
        "meeting_states_game_id_game_instances_id_fk": {
          "name": "meeting_states_game_id_game_instances_id_fk",
          "tableFrom": "meeting_states",
          "tableTo": "game_instances",
          "columnsFrom": [
            "game_id"
          ],
          "columnsTo": [
            "id"
          ],
          "onDelete": "no action",
          "onUpdate": "no action"
        },
        "meeting_states_triggered_by_players_in_game_id_fk": {
          "name": "meeting_states_triggered_by_players_in_game_id_fk",
          "tableFrom": "meeting_states",
          "tableTo": "players_in_game",
          "columnsFrom": [
            "triggered_by"
          ],
          "columnsTo": [
            "id"
          ],
          "onDelete": "no action",
          "onUpdate": "no action"
        }
      },
      "compositePrimaryKeys": {},
      "uniqueConstraints": {},
      "policies": {},
      "checkConstraints": {},
      "isRLSEnabled": false
    },
    "public.players_in_game": {
      "name": "players_in_game",
      "schema": "",
      "columns": {
        "id": {
          "name": "id",
          "type": "uuid",
          "primaryKey": true,
          "notNull": true,
          "default": "gen_random_uuid()"
        },
        "game_id": {
          "name": "game_id",
          "type": "uuid",
          "primaryKey": false,
          "notNull": true
        },
        "guest_session_id": {
          "name": "guest_session_id",
          "type": "uuid",
          "primaryKey": false,
          "notNull": false
        },
        "admin_id": {
          "name": "admin_id",
          "type": "uuid",
          "primaryKey": false,
          "notNull": false
        },
        "pseudo": {
          "name": "pseudo",
          "type": "varchar(30)",
          "primaryKey": false,
          "notNull": true
        },
        "role": {
          "name": "role",
          "type": "player_role",
          "typeSchema": "public",
          "primaryKey": false,
          "notNull": false
        },
        "life_state": {
          "name": "life_state",
          "type": "player_life_state",
          "typeSchema": "public",
          "primaryKey": false,
          "notNull": true,
          "default": "'ALIVE'"
        },
        "is_connected": {
          "name": "is_connected",
          "type": "boolean",
          "primaryKey": false,
          "notNull": true,
          "default": true
        },
        "joined_at": {
          "name": "joined_at",
          "type": "timestamp",
          "primaryKey": false,
          "notNull": true,
          "default": "now()"
        }
      },
      "indexes": {},
      "foreignKeys": {
        "players_in_game_game_id_game_instances_id_fk": {
          "name": "players_in_game_game_id_game_instances_id_fk",
          "tableFrom": "players_in_game",
          "tableTo": "game_instances",
          "columnsFrom": [
            "game_id"
          ],
          "columnsTo": [
            "id"
          ],
          "onDelete": "no action",
          "onUpdate": "no action"
        },
        "players_in_game_guest_session_id_guest_sessions_id_fk": {
          "name": "players_in_game_guest_session_id_guest_sessions_id_fk",
          "tableFrom": "players_in_game",
          "tableTo": "guest_sessions",
          "columnsFrom": [
            "guest_session_id"
          ],
          "columnsTo": [
            "id"
          ],
          "onDelete": "no action",
          "onUpdate": "no action"
        },
        "players_in_game_admin_id_user_accounts_id_fk": {
          "name": "players_in_game_admin_id_user_accounts_id_fk",
          "tableFrom": "players_in_game",
          "tableTo": "user_accounts",
          "columnsFrom": [
            "admin_id"
          ],
          "columnsTo": [
            "id"
          ],
          "onDelete": "no action",
          "onUpdate": "no action"
        }
      },
      "compositePrimaryKeys": {},
      "uniqueConstraints": {},
      "policies": {},
      "checkConstraints": {},
      "isRLSEnabled": false
    },
    "public.presets": {
      "name": "presets",
      "schema": "",
      "columns": {
        "id": {
          "name": "id",
          "type": "uuid",
          "primaryKey": true,
          "notNull": true,
          "default": "gen_random_uuid()"
        },
        "code": {
          "name": "code",
          "type": "varchar(20)",
          "primaryKey": false,
          "notNull": true
        },
        "name": {
          "name": "name",
          "type": "varchar(100)",
          "primaryKey": false,
          "notNull": true
        },
        "config_json": {
          "name": "config_json",
          "type": "jsonb",
          "primaryKey": false,
          "notNull": true
        },
        "created_at": {
          "name": "created_at",
          "type": "timestamp",
          "primaryKey": false,
          "notNull": true,
          "default": "now()"
        }
      },
      "indexes": {},
      "foreignKeys": {},
      "compositePrimaryKeys": {},
      "uniqueConstraints": {
        "presets_code_unique": {
          "name": "presets_code_unique",
          "nullsNotDistinct": false,
          "columns": [
            "code"
          ]
        }
      },
      "policies": {},
      "checkConstraints": {},
      "isRLSEnabled": false
    },
    "public.sabotage_states": {
      "name": "sabotage_states",
      "schema": "",
      "columns": {
        "id": {
          "name": "id",
          "type": "uuid",
          "primaryKey": true,
          "notNull": true,
          "default": "gen_random_uuid()"
        },
        "game_id": {
          "name": "game_id",
          "type": "uuid",
          "primaryKey": false,
          "notNull": true
        },
        "state": {
          "name": "state",
          "type": "sabotage_state",
          "typeSchema": "public",
          "primaryKey": false,
          "notNull": true,
          "default": "'NONE'"
        },
        "type": {
          "name": "type",
          "type": "sabotage_type",
          "typeSchema": "public",
          "primaryKey": false,
          "notNull": false
        },
        "triggered_by": {
          "name": "triggered_by",
          "type": "uuid",
          "primaryKey": false,
          "notNull": false
        },
        "timer_ends_at": {
          "name": "timer_ends_at",
          "type": "timestamp",
          "primaryKey": false,
          "notNull": false
        },
        "cooldown_ends_at": {
          "name": "cooldown_ends_at",
          "type": "timestamp",
          "primaryKey": false,
          "notNull": false
        },
        "created_at": {
          "name": "created_at",
          "type": "timestamp",
          "primaryKey": false,
          "notNull": true,
          "default": "now()"
        }
      },
      "indexes": {},
      "foreignKeys": {
        "sabotage_states_game_id_game_instances_id_fk": {
          "name": "sabotage_states_game_id_game_instances_id_fk",
          "tableFrom": "sabotage_states",
          "tableTo": "game_instances",
          "columnsFrom": [
            "game_id"
          ],
          "columnsTo": [
            "id"
          ],
          "onDelete": "no action",
          "onUpdate": "no action"
        },
        "sabotage_states_triggered_by_players_in_game_id_fk": {
          "name": "sabotage_states_triggered_by_players_in_game_id_fk",
          "tableFrom": "sabotage_states",
          "tableTo": "players_in_game",
          "columnsFrom": [
            "triggered_by"
          ],
          "columnsTo": [
            "id"
          ],
          "onDelete": "no action",
          "onUpdate": "no action"
        }
      },
      "compositePrimaryKeys": {},
      "uniqueConstraints": {},
      "policies": {},
      "checkConstraints": {},
      "isRLSEnabled": false
    },
    "public.tasks": {
      "name": "tasks",
      "schema": "",
      "columns": {
        "id": {
          "name": "id",
          "type": "uuid",
          "primaryKey": true,
          "notNull": true,
          "default": "gen_random_uuid()"
        },
        "game_id": {
          "name": "game_id",
          "type": "uuid",
          "primaryKey": false,
          "notNull": true
        },
        "name": {
          "name": "name",
          "type": "varchar(200)",
          "primaryKey": false,
          "notNull": true
        },
        "description": {
          "name": "description",
          "type": "text",
          "primaryKey": false,
          "notNull": true,
          "default": "''"
        },
        "is_completed": {
          "name": "is_completed",
          "type": "boolean",
          "primaryKey": false,
          "notNull": true,
          "default": false
        },
        "completed_by": {
          "name": "completed_by",
          "type": "uuid",
          "primaryKey": false,
          "notNull": false
        },
        "completed_at": {
          "name": "completed_at",
          "type": "timestamp",
          "primaryKey": false,
          "notNull": false
        }
      },
      "indexes": {},
      "foreignKeys": {
        "tasks_game_id_game_instances_id_fk": {
          "name": "tasks_game_id_game_instances_id_fk",
          "tableFrom": "tasks",
          "tableTo": "game_instances",
          "columnsFrom": [
            "game_id"
          ],
          "columnsTo": [
            "id"
          ],
          "onDelete": "no action",
          "onUpdate": "no action"
        },
        "tasks_completed_by_players_in_game_id_fk": {
          "name": "tasks_completed_by_players_in_game_id_fk",
          "tableFrom": "tasks",
          "tableTo": "players_in_game",
          "columnsFrom": [
            "completed_by"
          ],
          "columnsTo": [
            "id"
          ],
          "onDelete": "no action",
          "onUpdate": "no action"
        }
      },
      "compositePrimaryKeys": {},
      "uniqueConstraints": {},
      "policies": {},
      "checkConstraints": {},
      "isRLSEnabled": false
    },
    "public.user_accounts": {
      "name": "user_accounts",
      "schema": "",
      "columns": {
        "id": {
          "name": "id",
          "type": "uuid",
          "primaryKey": true,
          "notNull": true,
          "default": "gen_random_uuid()"
        },
        "username": {
          "name": "username",
          "type": "varchar(50)",
          "primaryKey": false,
          "notNull": true
        },
        "password_hash": {
          "name": "password_hash",
          "type": "text",
          "primaryKey": false,
          "notNull": true
        },
        "created_at": {
          "name": "created_at",
          "type": "timestamp",
          "primaryKey": false,
          "notNull": true,
          "default": "now()"
        }
      },
      "indexes": {},
      "foreignKeys": {},
      "compositePrimaryKeys": {},
      "uniqueConstraints": {
        "user_accounts_username_unique": {
          "name": "user_accounts_username_unique",
          "nullsNotDistinct": false,
          "columns": [
            "username"
          ]
        }
      },
      "policies": {},
      "checkConstraints": {},
      "isRLSEnabled": false
    },
    "public.votes": {
      "name": "votes",
      "schema": "",
      "columns": {
        "id": {
          "name": "id",
          "type": "uuid",
          "primaryKey": true,
          "notNull": true,
          "default": "gen_random_uuid()"
        },
        "meeting_id": {
          "name": "meeting_id",
          "type": "uuid",
          "primaryKey": false,
          "notNull": true
        },
        "voter_id": {
          "name": "voter_id",
          "type": "uuid",
          "primaryKey": false,
          "notNull": true
        },
        "target_id": {
          "name": "target_id",
          "type": "uuid",
          "primaryKey": false,
          "notNull": false
        },
        "created_at": {
          "name": "created_at",
          "type": "timestamp",
          "primaryKey": false,
          "notNull": true,
          "default": "now()"
        }
      },
      "indexes": {},
      "foreignKeys": {
        "votes_meeting_id_meeting_states_id_fk": {
          "name": "votes_meeting_id_meeting_states_id_fk",
          "tableFrom": "votes",
          "tableTo": "meeting_states",
          "columnsFrom": [
            "meeting_id"
          ],
          "columnsTo": [
            "id"
          ],
          "onDelete": "no action",
          "onUpdate": "no action"
        },
        "votes_voter_id_players_in_game_id_fk": {
          "name": "votes_voter_id_players_in_game_id_fk",
          "tableFrom": "votes",
          "tableTo": "players_in_game",
          "columnsFrom": [
            "voter_id"
          ],
          "columnsTo": [
            "id"
          ],
          "onDelete": "no action",
          "onUpdate": "no action"
        },
        "votes_target_id_players_in_game_id_fk": {
          "name": "votes_target_id_players_in_game_id_fk",
          "tableFrom": "votes",
          "tableTo": "players_in_game",
          "columnsFrom": [
            "target_id"
          ],
          "columnsTo": [
            "id"
          ],
          "onDelete": "no action",
          "onUpdate": "no action"
        }
      },
      "compositePrimaryKeys": {},
      "uniqueConstraints": {},
      "policies": {},
      "checkConstraints": {},
      "isRLSEnabled": false
    }
  },
  "enums": {
    "public.game_phase": {
      "name": "game_phase",
      "schema": "public",
      "values": [
        "FREE_ROAM",
        "MEETING_IN_PROGRESS",
        "GAME_OVER_PENDING"
      ]
    },
    "public.game_status": {
      "name": "game_status",
      "schema": "public",
      "values": [
        "DRAFT",
        "LOBBY_OPEN",
        "READY",
        "RUNNING",
        "ENDED",
        "CANCELLED"
      ]
    },
    "public.meeting_state": {
      "name": "meeting_state",
      "schema": "public",
      "values": [
        "IDLE",
        "REQUESTED",
        "OPEN",
        "DISCUSSION",
        "VOTING",
        "RESOLVING",
        "CLOSED"
      ]
    },
    "public.player_life_state": {
      "name": "player_life_state",
      "schema": "public",
      "values": [
        "ALIVE",
        "DEAD",
        "EJECTED"
      ]
    },
    "public.player_role": {
      "name": "player_role",
      "schema": "public",
      "values": [
        "CREWMATE",
        "IMPOSTOR"
      ]
    },
    "public.sabotage_state": {
      "name": "sabotage_state",
      "schema": "public",
      "values": [
        "NONE",
        "STARTING",
        "ACTIVE",
        "RESOLVING",
        "RESOLVED",
        "FAILED",
        "COOLDOWN"
      ]
    },
    "public.sabotage_type": {
      "name": "sabotage_type",
      "schema": "public",
      "values": [
        "OXYGEN",
        "ENERGY"
      ]
    },
    "public.task_validation_mode": {
      "name": "task_validation_mode",
      "schema": "public",
      "values": [
        "ANY_PLAYER",
        "ADMIN_ONLY"
      ]
    }
  },
  "schemas": {},
  "sequences": {},
  "roles": {},
  "policies": {},
  "views": {},
  "_meta": {
    "columns": {},
    "schemas": {},
    "tables": {}
  }
}